flaris/__init__.py
flaris/audio.py
flaris/component.py
flaris/entity.py
flaris/game.py
flaris/system.py
flaris/transform.py
flaris/assets/__init__.py
flaris/assets/fonts/Moon Light.otf
flaris/inputs/__init__.py
flaris/inputs/key.py
flaris/inputs/systems.py
flaris/rendering/__init__.py
flaris/rendering/character.py
flaris/rendering/color.py
flaris/rendering/font.py
flaris/rendering/icon.py
flaris/rendering/shader.py
flaris/rendering/sprite.py
flaris/rendering/systems.py
flaris/rendering/text.py
flaris/rendering/texture.py
flaris/rendering/window.py
flaris/rendering/renderers/__init__.py
flaris/rendering/renderers/sprite.py
flaris/rendering/renderers/text.py
framework/__init__.py
framework/audio.py
framework/component.py
framework/entity.py
framework/game.py
framework/resource.py
framework/system.py
framework/transform.py
framework/assets/fonts/Moon Light.otf
framework/inputs/__init__.py
framework/inputs/key.py
framework/inputs/systems.py
framework/rendering/__init__.py
framework/rendering/character.py
framework/rendering/color.py
framework/rendering/font.py
framework/rendering/icon.py
framework/rendering/shader.py
framework/rendering/sprite.py
framework/rendering/systems.py
framework/rendering/text.py
framework/rendering/texture.py
framework/rendering/window.py
framework/rendering/renderers/__init__.py
framework/rendering/renderers/sprite.py
framework/rendering/renderers/text.py
test/__init__.py
test/unit/__init__.py
test/unit/flaris/__init__.py
test/unit/flaris/test_transform.py
test/unit/flaris/rendering/__init__.py
test/unit/flaris/rendering/test_icon.py
test/unit/flaris/rendering/test_texture.py
test/unit/flaris/rendering/test_window.py
test/unit/framework/__init__.py
test/unit/framework/test_transform.py
test/unit/framework/rendering/__init__.py
test/unit/framework/rendering/test_icon.py
test/unit/framework/rendering/test_texture.py
test/unit/framework/rendering/test_window.py
flaris-0.1.0.dist-info/LICENSE
flaris-0.1.0.dist-info/METADATA
flaris-0.1.0.dist-info/WHEEL
flaris-0.1.0.dist-info/top_level.txt
flaris-0.1.0.dist-info/RECORD
